altility/__init__.py
altility/adl_model.py
altility/datasets/__init__.py
altility/datasets/load_forecasting.py
altility/datasets/travel_forecasting.py
altility-0.0.3.dist-info/METADATA
altility-0.0.3.dist-info/WHEEL
altility-0.0.3.dist-info/top_level.txt
altility-0.0.3.dist-info/RECORD
