Metadata-Version: 2.1
Name: altility
Version: 0.0.3
Summary: Enhanced spatio-temporal predictions using less data with active deep learning
Home-page: UNKNOWN
Author: Arsam Aryandoust
Author-email: arsama@ethz.ch
License: UNKNOWN
Project-URL: Code repository, https://github.com/ArsamAryandoust/altility
Platform: UNKNOWN
Classifier: Programming Language :: Python :: 3
Classifier: License :: OSI Approved :: MIT License
Classifier: Operating System :: OS Independent
Requires-Dist: numpy (>=1.20.0)
Requires-Dist: pandas (>=1.3.0)
Requires-Dist: matplotlib (>=3.4.0)
Requires-Dist: tensorflow (>=2.7.0)
Requires-Dist: sklearn (>=1.0.2)
